pyjdpu/__init__.py
pyjdpu/__main__.py
pyjdpu-1.0.0.dist-info/LICENSE
pyjdpu-1.0.0.dist-info/METADATA
pyjdpu-1.0.0.dist-info/WHEEL
pyjdpu-1.0.0.dist-info/entry_points.txt
pyjdpu-1.0.0.dist-info/top_level.txt
pyjdpu-1.0.0.dist-info/RECORD
